quspin-1.0.0.dist-info/METADATA
quspin-1.0.0.dist-info/WHEEL
quspin-1.0.0.dist-info/entry_points.txt
quspin-1.0.0.dist-info/licenses/LICENSE.rst
quspin/__init__.py
quspin/basis/__init__.py
quspin/basis/_reshape_subsys.py
quspin/basis/base.py
quspin/basis/basis_1d/__init__.py
quspin/basis/basis_1d/_check_1d_symm.py
quspin/basis/basis_1d/_check_1d_symm_spf.py
quspin/basis/basis_1d/base_1d.py
quspin/basis/basis_1d/boson.py
quspin/basis/basis_1d/fermion.py
quspin/basis/basis_1d/spin.py
quspin/basis/basis_general/__init__.py
quspin/basis/basis_general/base_general.py
quspin/basis/basis_general/base_hcb.py
quspin/basis/basis_general/base_higher_spin.py
quspin/basis/basis_general/base_user.py
quspin/basis/basis_general/boson.py
quspin/basis/basis_general/fermion.py
quspin/basis/basis_general/spin.py
quspin/basis/lattice.py
quspin/basis/photon.py
quspin/basis/tensor.py
quspin/basis/transformations/__init__.py
quspin/basis/transformations/site_info.py
quspin/basis/transformations/square.py
quspin/basis/user.py
quspin/operators/__init__.py
quspin/operators/_functions.py
quspin/operators/_make_hamiltonian.py
quspin/operators/exp_op_core.py
quspin/operators/hamiltonian_core.py
quspin/operators/quantum_LinearOperator_core.py
quspin/operators/quantum_operator_core.py
quspin/tools/Floquet.py
quspin/tools/__init__.py
quspin/tools/block_tools.py
quspin/tools/evolution.py
quspin/tools/expm_multiply_parallel_core/__init__.py
quspin/tools/lanczos/_FTLM.py
quspin/tools/lanczos/_LTLM.py
quspin/tools/lanczos/__init__.py
quspin/tools/lanczos/_expm.py
quspin/tools/lanczos/_lanczos_utils.py
quspin/tools/matvec/__init__.py
quspin/tools/measurements.py
quspin/tools/misc.py
quspin-1.0.0.dist-info/RECORD
