Metadata-Version: 2.1
Name: quspin
Version: 1.0.0
Summary: A Python package for exact diagonalization calculations of quantum manybody systems.
Author-Email: "Phillip Weinberg, Marin Bukov" <weinbe58@gmail.com>
License: BDS-3
Requires-Python: <3.13,>=3.9
Requires-Dist: quspin-extensions>=0.1.3
Requires-Dist: parallel-sparse-tools>=0.1.3
Requires-Dist: numpy>=2.0.0
Requires-Dist: dill>=0.3.8
Requires-Dist: scipy>=1.13.1
Requires-Dist: matplotlib>=3.9.0
Requires-Dist: numexpr>=2.10.1
Requires-Dist: numba>=0.60.0
Requires-Dist: six>=1.16.0
Requires-Dist: joblib>=1.4.2
